{
  "solicitudes": [],
  "historial": [
    {
      "0": {
        "id": "023e",
        "nombreUsuario": "UsuarioTest",
        "codigoComputadora": "2131",
        "sede": "sedeNosara",
        "fechaSalida": "2024-08-23",
        "fechaRegreso": "2024-08-26"
      },
      "id": "9f52"
    },
    {
      "0": {
        "id": "f2d9",
        "nombreUsuario": "UsuarioTest",
        "codigoComputadora": "344645",
        "sede": "sedePuntarenas",
        "fechaSalida": "2024-08-24",
        "fechaRegreso": "2024-08-26"
      },
      "id": "e690"
    }
  ]
}